[{"text":".idea","prefix":"/.idea/","children":[]},{"text":"临时","prefix":"/linshi/","children":[]},{"text":"其他","prefix":"/qita/","children":[{"text":"work","link":"work/"},{"text":"todo","link":"todo/"},{"text":"2023","link":"2023/"},{"text":"2024","link":"2024/"},{"text":"历史","link":"lishi/"},{"text":"大唐","link":"datang/"},{"text":"生活知识点","link":"shenghuozhishidian/"}]},{"text":"基础","prefix":"/jichu/","children":[{"text":"html与css","link":"htmlyucss/"},{"text":"JavaScript","link":"JavaScript/"},{"text":"openlayers","link":"openlayers/"},{"text":"工具","link":"gongju/"},{"text":"框架","link":"kuangjia/"}]},{"text":"进阶","prefix":"/jinjie/","children":[{"text":"html","link":"html/"},{"text":"组件","link":"zujian/"}]},{"text":"面试","prefix":"/mianshi/","children":[{"text":"简历","link":"jianli/"},{"text":"面试题","link":"mianshiti/"},{"text":"性能","link":"xingneng/"}]},{"text":"项目","prefix":"/xiangmu/","children":[{"text":"后台管理","link":"houtaiguanli/"},{"text":"base","link":"base/"}]}]